pyElsHelp/__init__.py
pyElsHelp/functions.py
pyElsHelp-0.0.2.dist-info/METADATA
pyElsHelp-0.0.2.dist-info/WHEEL
pyElsHelp-0.0.2.dist-info/top_level.txt
pyElsHelp-0.0.2.dist-info/RECORD
