Metadata-Version: 2.1
Name: pyElsHelp
Version: 0.0.2
Summary: This is the module for ELSCHOOL diary
Home-page: https://github.com/theslothbear/Elschool-Help-Bot
Author: the_sloth_bear
Author-email: molnychess@yandex.ru
License: UNKNOWN
Project-URL: GitHub, https://github.com/theslothbear
Keywords: pyElsHelp
Platform: UNKNOWN
Classifier: Programming Language :: Python :: 3.11
Classifier: License :: OSI Approved :: MIT License
Classifier: Operating System :: OS Independent
Requires-Python: >=3.6
Requires-Dist: requests >=2.25.1
